cute_sleeper/__init__.py
cute_sleeper/sleeper.py
cute_sleeper-0.2.dist-info/LICENSE
cute_sleeper-0.2.dist-info/METADATA
cute_sleeper-0.2.dist-info/WHEEL
cute_sleeper-0.2.dist-info/top_level.txt
cute_sleeper-0.2.dist-info/RECORD
