Metadata-Version: 2.1
Name: cute-sleeper
Version: 0.2
Summary: A simple Python library for random sleep times based on normal distribution
Home-page: https://github.com/Aramir94/sleeper
Author: data_jeong
Author-email: jhs941222@naver.com
License: Apache
License-File: LICENSE
